{
	"pages": [ //pages数组中第一项表示应用启动页，参考：https://uniapp.dcloud.io/collocation/pages
		{
			"path": "pages/index/index",
			"style": {
				"navigationBarTitleText": "uni-app"
			}
		}
	    ,{
            "path" : "pages/logs/logs",
            "style" :                                                                                    
            {
                "navigationBarTitleText": "",
                "enablePullDownRefresh": false
            }
            
        }
    ],
	"globalStyle": {
		"navigationBarTextStyle": "black",
		"navigationBarTitleText": "uni-app",
		"navigationBarBackgroundColor": "#F8F8F8",
		"backgroundColor": "#F8F8F8"
	},
	"uniIdRouter": {},
	"tabBar": {
		// #ifdef MP-WEIXIN | MP-QQ
	    "custom": true,
		// #endif
		// #ifdef MP-ALIPAY
		"customize": true,
		// #endif
		"color": "#000",
		"selectedColor": "#ff0000",
		"borderStyle": "black",
		"backgroundColor": "#09c",
		"list": [{
			"pagePath": "pages/index/index",
			"text": "首页"
		}, {
			"pagePath": "pages/logs/logs",
			"text": "日志"
		}]
	}
}
